stac_fastapi/elasticsearch/__init__.py
stac_fastapi/elasticsearch/app.py
stac_fastapi/elasticsearch/config.py
stac_fastapi/elasticsearch/database_logic.py
stac_fastapi/elasticsearch/version.py
stac_fastapi_elasticsearch-6.10.0.dist-info/METADATA
stac_fastapi_elasticsearch-6.10.0.dist-info/WHEEL
stac_fastapi_elasticsearch-6.10.0.dist-info/entry_points.txt
stac_fastapi_elasticsearch-6.10.0.dist-info/RECORD
