Metadata-Version: 2.4
Name: stac_fastapi_elasticsearch
Version: 6.10.0
Summary: An implementation of STAC API based on the FastAPI framework with Elasticsearch.
Project-URL: Homepage, https://github.com/stac-utils/stac-fastapi-elasticsearch-opensearch
License: MIT
Keywords: Elasticsearch,FastAPI,STAC,STAC-API,stac-fastapi
Classifier: Intended Audience :: Developers
Classifier: Intended Audience :: Information Technology
Classifier: Intended Audience :: Science/Research
Classifier: License :: OSI Approved :: MIT License
Classifier: Programming Language :: Python :: 3.11
Classifier: Programming Language :: Python :: 3.12
Classifier: Programming Language :: Python :: 3.13
Classifier: Programming Language :: Python :: 3.14
Requires-Python: >=3.11
Requires-Dist: elasticsearch[async]~=8.19.1
Requires-Dist: sfeos-helpers==6.10.0
Requires-Dist: stac-fastapi-core==6.10.0
Requires-Dist: starlette<0.36.0,>=0.35.0
Requires-Dist: uvicorn~=0.23.0
Provides-Extra: dev
Requires-Dist: ciso8601~=2.3.0; extra == 'dev'
Requires-Dist: httpx<0.28.0,>=0.24.0; extra == 'dev'
Requires-Dist: pre-commit~=3.0.0; extra == 'dev'
Requires-Dist: pytest-asyncio~=0.21.0; extra == 'dev'
Requires-Dist: pytest-cov~=4.0.0; extra == 'dev'
Requires-Dist: pytest~=8.0; extra == 'dev'
Requires-Dist: redis~=6.4.0; extra == 'dev'
Requires-Dist: retry~=0.9.2; extra == 'dev'
Requires-Dist: stac-fastapi-core[redis]==6.10.0; extra == 'dev'
Provides-Extra: docs
Requires-Dist: mkdocs-material~=9.0.0; extra == 'docs'
Requires-Dist: mkdocs~=1.4.0; extra == 'docs'
Requires-Dist: pdocs~=1.2.0; extra == 'docs'
Requires-Dist: redis~=6.4.0; extra == 'docs'
Requires-Dist: retry~=0.9.2; extra == 'docs'
Provides-Extra: redis
Requires-Dist: stac-fastapi-core[redis]==6.10.0; extra == 'redis'
Provides-Extra: server
Requires-Dist: uvicorn[standard]~=0.23.0; extra == 'server'
